{
  "subreddits": ["airbnb_hosts", "AirBnB", "realestateinvesting"],
  "seedKeywords": [
    "airbnb london",
    "airbnb hosting",
    "short term rental uk",
    "property management london",
    "holiday let london",
    "renters rights act"
  ],
  "trendsGeo": "GB",
  "defaultCategory": "Property Management",
  "author": {
    "name": "Host My Nest",
    "bio": "Host My Nest specialises in creating memorable stays with exceptional service and attention to detail. Our properties offer comfort, style, and all the amenities you need for a stress-free experience. From seamless check-ins to spotlessly clean spaces, we ensure every guest feels right at home. Whether you're here for business or leisure, let us make your stay unforgettable."
  }
}
